Workbook

Sheet Instrucciones
A1: MATRIZ DE REQUERIMIENTOS - PROTOCEM
A2: Proyectos Topograficos y Construcciones | Modelado de Requerimientos | UAA 2025
A4: Proposito de esta matriz
A5: Esta matriz documenta, prioriza y da seguimiento a los requerimientos identificados en la entrevista con el Ing. Carlos Macias Chairez de Protocem.
A6: Disenada para refinamiento iterativo: se puede ir agregando y modificando conforme avanzan las entrevistas.
A8: Como usar esta plantilla:
A9: 1. Vayan a la pestana 'RF - Funcionales' y documenten todos los requerimientos funcionales identificados.
A10: 2. Vayan a la pestana 'RNF - No Funcionales' y documenten los no funcionales.
A11: 3. La pestana 'Resumen' muestra estadisticas automaticas con formulas.
A12: 4. Usen los filtros de las columnas para ordenar por prioridad, estado, etc.
A14: Descripcion de columnas:
A15: ID: Identificador unico. Formato RF-01... para funcionales; RNF-01... para no funcionales.
... A28: X No indicar fuente -> Rastrear quien lo pidio

Sheet RF - Funcionales
A1: ID | B1: Descripcion | C1: Criterio de Aceptacion | D1: Prioridad | E1: Fuente | F1: Estado | G1: Version | H1: Notas
A2: RF-01 | B2: El sistema debe permitir registrar nuevos proyectos de obra con nombre, fecha de inicio, fecha estimada de entrega y presupuesto total aprobado. | C2: Se crea un proyecto con todos los campos obligatorios. El sistema rechaza el registro si el presupuesto es cero o negativo. El proyecto queda visible en el listado de proyectos activos. | D2: Must have | E2: Ing. Carlos Macias (Administrador) - Entrevista 1 | F2: Validado internamente | G2: 1.0 | H2: Aplica a obra publica y privada. En obra publica el presupuesto es fijo e inamovible.
A3: RF-02 | B3: El sistema debe permitir registrar compras de material vinculadas a un proyecto especifico, incluyendo fecha, proveedor, materiales comprados, cantidades y precio real pagado por unidad. | C3: Al registrar una compra, el sistema la asocia automaticamente al proyecto seleccionado. El gasto acumulado del proyecto se actualiza inmediatamente. No se puede registrar una compra sin seleccionar proyecto. | D3: Must have | E3: Ing. Carlos Macias - Entrevista 1 | F3: Validado internamente | G3: 1.0 | H3: Actualmente las notas de compra se vacian manualmente en Excel. El sistema reemplaza ese proceso.
A4: RF-03 | B4: El sistema debe mantener un catalogo de materiales (cemento, grava, arena, agua, acero, etc.) con stock actual que se actualiza automaticamente al registrar compras y salidas. | C4: Despues de registrar una compra de 100 bultos de cemento, el stock del producto aumenta en 100. Despues de registrar una salida de 30 bultos, el stock disminuye a 70. El sistema muestra el stock en tiempo real. | D4: Must have | E4: Ing. Carlos Macias - Entrevista 1 | F4: Validado internamente | G4: 1.0 | H4: El control de inventario fue identificado como el proceso mas descuidado. El stock nunca puede ser negativo.
A5: RF-04 | B5: El sistema debe registrar cada salida de material de bodega hacia la obra, indicando fecha, responsable, tipo de salida (consumo, merma, robo, prestamo) y proyecto al que corresponde. | C5: Se registra una salida con todos los campos. El stock del producto disminuye automaticamente. El reporte de salidas por proyecto muestra el historico completo con tipo de salida. | D5: Must have | E5: Ing. Carlos Macias - Entrevista 1 | F5: Validado internamente | G5: 1.0 | H5: CRITICO: actualmente las salidas NO se registran en ningun lado. El velador cuida el material sin control formal.
A6: RF-05 | B6: El sistema debe permitir registrar cotizaciones de precios de materiales con distintos proveedores, guardando fecha, material, proveedor y precio cotizado. | C6: Se puede registrar multiples cotizaciones del mismo material con diferentes proveedores. El historial de cotizaciones es consultable por material o por proveedor. | D6: Must have | E6: Ing. Carlos Macias - Entrevista 1 | F6: Validado internamente | G6: 1.0 | H6: El ingeniero cotiza en Home Depot, Cruz Azul, Apasco. Actualmente no hay registro digital de estas cotizaciones.
A7: RF-06 | B7: El sistema debe comparar el precio cotizado en la licitacion versus el precio real de compra y mostrar el porcentaje de desviacion, con alerta visual cuando la desviacion supere el 5%. | C7: Para cada material, el sistema muestra: precio cotizado, precio real mas reciente, diferencia en pesos y porcentaje de desviacion. Si la desviacion supera el 5%, el sistema muestra indicador rojo. | D7: Must have | E7: Ing. Carlos Macias - Entrevista 1 | F7: Validado internamente | G7: 1.0 | H7: KPI prioritario mencionado por el ingeniero. Ejemplo: cotizo cemento a $260, ahora cuesta $350, desviacion del 34.6%.
A8: RF-07 | B8: El sistema debe mostrar en cualquier momento la rentabilidad de cada proyecto: presupuesto aprobado, gasto acumulado, saldo restante y porcentaje del presupuesto utilizado. | C8: El dashboard de proyecto muestra los 4 indicadores en tiempo real. Al agregar una compra nueva, los valores se actualizan automaticamente. El saldo restante nunca puede mostrarse incorrecto. | D8: Must have | E8: Ing. Carlos Macias - Entrevista 1 | F8: Validado internamente | G8: 1.0 | H8: Actualmente la rentabilidad solo se calcula al finalizar la obra. Esto impide decisiones correctivas a tiempo.
A9: RF-08 | B9: El sistema debe controlar el acceso mediante roles diferenciados: Administrador (acceso total), Encargado de obra (captura y consulta parcial), Solo lectura (solo visualizacion). | C9: Un usuario con rol Encargado puede registrar salidas pero no puede ver el presupuesto total ni las cotizaciones. Un usuario con rol Solo lectura no puede modificar ningun dato. El Administrador accede a todo. | D9: Must have | E9: Ing. Carlos Macias - Entrevista 1 | F9: Validado internamente | G9: 1.0 | H9: El ingeniero fue explicitico: la informacion de cotizaciones es su ventaja competitiva. Nadie mas debe verla completa.
A10: RF-09 | B10: El sistema debe permitir actualizar el porcentaje de avance fisico de cada proyecto y mantener un historial de avance con fecha de cada actualizacion. | C10: Se puede registrar un nuevo porcentaje de avance. El historial muestra fecha y valor de cada actualizacion. El porcentaje debe estar entre 0 y 100; el sistema rechaza valores fuera de rango. | D10: Should have | E10: Ing. Carlos Macias - Entrevista 1 | F10: Validado internamente | G10: 1.0 | H10: Actualmente el avance se lleva en un Excel separado sin vinculo con el control de gastos.
A11: RF-10 | B11: El sistema debe permitir gestionar un catalogo de proveedores con nombre, empresa, telefono y persona de contacto. | C11: Se pueden agregar, editar y consultar proveedores. Al registrar una cotizacion o compra, el proveedor se selecciona del catalogo existente (no se escribe texto libre). | D11: Should have | E11: Asistente administrativo - Entrevista 1 | F11: Validado internamente | G11: 1.0 | H11: Actualmente los contactos de proveedores estan solo en el celular del ingeniero. No existe un catalogo formal.
A12: RF-11 | B12: El sistema debe generar un reporte de movimientos de material por proyecto que muestre entradas (compras), salidas y saldo en inventario para cada material. | C12: El reporte filtra por proyecto y muestra todos los movimientos de cada material con fecha. El saldo en inventario es consistente: suma de entradas menos suma de salidas. | D12: Should have | E12: Ing. Carlos Macias - Entrevista 1 | F12: Validado internamente | G12: 1.0 | H12: Permite identificar mermas: si se compraron 100 bultos y se usaron 90, pero el saldo es 5, hay 5 perdidos.
... A14: RF-13 | B14: El sistema debe permitir adjuntar o referenciar los documentos de contrato de cada proyecto (numero de licitacion, monto contratado, cliente). | C14: Se puede registrar el numero de contrato y licitacion de cada proyecto. El campo es consultable y sirve como referencia para auditorias. | D14: Could have | E14: Ing. Carlos Macias - Entrevista 1 | F14: Propuesto | G14: 1.0 | H14: Protocem ha manejado contratos como INAGUA-2016-E08, FISM-002-036/2013, etc. Util para trazabilidad.

Sheet RNF - No Funcionales
A1: ID | B1: Categoria | C1: Descripcion | D1: Criterio de Aceptacion | E1: Prioridad | F1: Fuente | G1: Estado | H1: Version | I1: Notas
A2: RNF-01 | B2: Seguridad | C2: El sistema debe requerir autenticacion con correo y contrasena para acceder. Las contrasenas deben almacenarse cifradas (hash) y nunca en texto plano. | D2: Un intento de acceso sin credenciales validas es rechazado. La base de datos no contiene contrasenas en texto plano. Despues de 5 intentos fallidos, la cuenta se bloquea temporalmente. | E2: Must have | F2: Ing. Carlos Macias - Entrevista 1 | G2: Validado internamente | H2: 1.0 | I2: La informacion del sistema es competitivamente sensible. El ingeniero enfatizo que nadie mas puede acceder.
A3: RNF-02 | B3: Seguridad | C3: El sistema debe implementar control de acceso basado en roles (RBAC). Cada usuario solo puede ver y modificar la informacion que corresponde a su rol. | D3: Un usuario con rol Encargado que intente acceder a la seccion de cotizaciones o presupuestos recibe un mensaje de acceso denegado. Los registros de auditor muestran quien accedio a que. | E3: Must have | F3: Ing. Carlos Macias - Entrevista 1 | G3: Validado internamente | H3: 1.0 | I3: Roles definidos: Administrador, Encargado de obra, Solo lectura.
A4: RNF-03 | B4: Disponibilidad | C4: El sistema debe ser accesible desde navegador web en computadora de escritorio y desde dispositivos moviles (smartphone o tablet) sin necesidad de instalar aplicacion. | D4: El sistema funciona correctamente en Chrome/Edge en PC y en Chrome/Safari en Android/iOS. Los formularios de captura son usables en pantalla de 5 pulgadas. | E4: Must have | F4: Ing. Carlos Macias - Entrevista 1 | G4: Validado internamente | H4: 1.0 | I4: El ingeniero supervisa obra en campo y revisa avances desde casa. Necesita acceso desde cualquier dispositivo.
A5: RNF-04 | B5: Confiabilidad | C5: El sistema debe realizar respaldos automaticos de la base de datos al menos una vez al dia, con posibilidad de restauracion en caso de fallo. | D5: El sistema genera un backup diario. En caso de fallo, se puede restaurar la informacion del dia anterior con un proceso documentado de menos de 30 minutos. | E5: Must have | F5: Ing. Carlos Macias - Entrevista 1 | G5: Validado internamente | H5: 1.0 | I5: El ingeniero indico que la informacion es muy sensible y requiere respaldo. Obras de hasta $127M dependen de estos datos.
A6: RNF-05 | B6: Rendimiento | C6: El sistema debe responder a las consultas de uso cotidiano (gasto acumulado, stock actual, desviacion de precios) en menos de 3 segundos, incluso con datos de 5 o mas proyectos activos. | D6: Se ejecutan 20 consultas simultaneas de reportes de rentabilidad y ninguna tarda mas de 3 segundos. La prueba se realiza con al menos 3 proyectos con 100+ compras registradas cada uno. | E6: Should have | F6: Equipo de desarrollo | G6: Validado internamente | H6: 1.0 | I6: Protocem maneja proyectos de hasta 390 dias con muchas compras acumuladas. El rendimiento es critico para el uso diario.
A7: RNF-06 | B7: Integridad | C7: El sistema no debe permitir eliminar un proyecto que tenga compras, salidas o cotizaciones registradas. La informacion historica debe mantenerse integra. | D7: Al intentar eliminar un proyecto con compras asociadas, el sistema muestra un mensaje de error explicativo y no realiza la eliminacion. Solo es posible archivar proyectos finalizados. | E7: Must have | F7: Equipo de desarrollo | G7: Validado internamente | H7: 1.0 | I7: Relacionado con ON DELETE RESTRICT en el modelo relacional. Critico para auditoria de contratos publicos.
A8: RNF-07 | B8: Usabilidad | C8: Los formularios de captura de material y salidas deben poder completarse en menos de 2 minutos por un usuario sin conocimientos tecnicos avanzados. | D8: Un usuario con rol Encargado, tras 15 minutos de capacitacion, puede registrar una salida de material completa en menos de 2 minutos sin asistencia. | E8: Should have | F8: Encargado de obra / Velador - Entrevista 1 | G8: Propuesto | H8: 1.0 | I8: El velador y los encargados de obra no son tecnicos. Si el sistema es complicado, no lo usaran.
A9: RNF-08 | B9: Privacidad | C9: La informacion de cotizaciones y presupuestos no debe ser accesible desde fuera del sistema ni transmitirse sin cifrado. La conexion debe usar HTTPS. | D9: Toda comunicacion entre cliente y servidor usa HTTPS. Un intento de acceso directo a la base de datos desde fuera del servidor es bloqueado. Las cotizaciones no aparecen en resultados de busqueda web. | E9: Must have | F9: Ing. Carlos Macias - Entrevista 1 | G9: Validado internamente | H9: 1.0 | I9: El ingeniero menciono explicitamente el riesgo de que competidores accedan a su forma de cotizar.
A10: RNF-09 | B10: Escalabilidad | C10: El sistema debe soportar el registro de al menos 20 proyectos simultaneos con sus compras, salidas y cotizaciones sin degradacion de rendimiento. | D10: Con 20 proyectos activos y 500+ movimientos por proyecto, el tiempo de respuesta no supera los 3 segundos en consultas de reporte. | E10: Should have | F10: Equipo de desarrollo | G10: Propuesto | H10: 1.0 | I10: Protocem ha manejado contratos de hasta $127M (Fujita) con cientos de compras. El volumen puede crecer.
A11: RNF-10 | B11: Mantenibilidad | C11: El codigo y la estructura de la base de datos deben estar documentados para permitir modificaciones futuras sin necesidad de redisenar el sistema. | D11: Existe un documento tecnico con el diagrama ER, el esquema SQL comentado y la descripcion de cada tabla. Un desarrollador nuevo puede entender la estructura en menos de 2 horas. | E11: Could have | F11: Equipo de desarrollo | G11: Propuesto | H11: 1.0 | I11: Protocem puede necesitar agregar funcionalidades como pagos a contratistas (RF-12) en versiones futuras.

Sheet Resumen
A1: RESUMEN DE REQUERIMIENTOS - PROTOCEM
A2: Proyectos Topograficos y Construcciones | UAA 2025
A4: TOTALES
A5: Total RF (Requerimientos Funcionales) | B5: =COUNTA('RF - Funcionales'!A2:A200)
A6: Total RNF (Requerimientos No Funcionales) | B6: =COUNTA('RNF - No Funcionales'!A2:A200)
A7: TOTAL GENERAL | B7: =B5+B6
A9: POR PRIORIDAD (RF + RNF)
A10: Must have | B10: =COUNTIF('RF - Funcionales'!D2:D200,"Must have")+COUNTIF('RNF - No Funcionales'!E2:E200,"Must have")
A11: Should have | B11: =COUNTIF('RF - Funcionales'!D2:D200,"Should have")+COUNTIF('RNF - No Funcionales'!E2:E200,"Should have")
A12: Could have | B12: =COUNTIF('RF - Funcionales'!D2:D200,"Could have")+COUNTIF('RNF - No Funcionales'!E2:E200,"Could have")
A13: Won't have | B13: =COUNTIF('RF - Funcionales'!D2:D200,"Won't have")+COUNTIF('RNF - No Funcionales'!E2:E200,"Won't have")
A15: POR ESTADO (RF + RNF)
A16: Propuesto | B16: =COUNTIF('RF - Funcionales'!F2:F200,"Propuesto")+COUNTIF('RNF - No Funcionales'!G2:G200,"Propuesto")
A17: En revision | B17: =COUNTIF('RF - Funcionales'!F2:F200,"En revision")+COUNTIF('RNF - No Funcionales'!G2:G200,"En revision")
A18: Validado internamente | B18: =COUNTIF('RF - Funcionales'!F2:F200,"Validado internamente")+COUNTIF('RNF - No Funcionales'!G2:G200,"Validado internamente")
A19: Validado con cliente | B19: =COUNTIF('RF - Funcionales'!F2:F200,"Validado con cliente")+COUNTIF('RNF - No Funcionales'!G2:G200,"Validado con cliente")
A20: Rechazado | B20: =COUNTIF('RF - Funcionales'!F2:F200,"Rechazado")+COUNTIF('RNF - No Funcionales'!G2:G200,"Rechazado")
A22: RF POR PRIORIDAD
A23: Must have (solo RF) | B23: =COUNTIF('RF - Funcionales'!D2:D200,"Must have")
A24: Should have (solo RF) | B24: =COUNTIF('RF - Funcionales'!D2:D200,"Should have")
A25: Could have (solo RF) | B25: =COUNTIF('RF - Funcionales'!D2:D200,"Could have")
A27: RNF POR CATEGORIA
A28: Seguridad | B28: =COUNTIF('RNF - No Funcionales'!B2:B200,"Seguridad")
A29: Disponibilidad | B29: =COUNTIF('RNF - No Funcionales'!B2:B200,"Disponibilidad")
A30: Confiabilidad | B30: =COUNTIF('RNF - No Funcionales'!B2:B200,"Confiabilidad")
A31: Rendimiento | B31: =COUNTIF('RNF - No Funcionales'!B2:B200,"Rendimiento")
A32: Integridad | B32: =COUNTIF('RNF - No Funcionales'!B2:B200,"Integridad")
A33: Usabilidad | B33: =COUNTIF('RNF - No Funcionales'!B2:B200,"Usabilidad")
A34: Privacidad | B34: =COUNTIF('RNF - No Funcionales'!B2:B200,"Privacidad")
A35: Escalabilidad | B35: =COUNTIF('RNF - No Funcionales'!B2:B200,"Escalabilidad")
A36: Mantenibilidad | B36: =COUNTIF('RNF - No Funcionales'!B2:B200,"Mantenibilidad")
